genopy/__init__.py
genopy-0.0.2.dist-info/LICENSE.txt
genopy-0.0.2.dist-info/METADATA
genopy-0.0.2.dist-info/WHEEL
genopy-0.0.2.dist-info/top_level.txt
genopy-0.0.2.dist-info/RECORD
