Metadata-Version: 2.1
Name: genopy
Version: 0.0.2
Summary: Analyses genetiques et phylogenetiques
Home-page: UNKNOWN
Author: Yann Bouyeron
Author-email: yann.bouyeron@hotmail.fr
License: UNKNOWN
Project-URL: Source, https://github.com/YannBouyeron/genopy/
Platform: UNKNOWN
Classifier: Development Status :: 3 - Alpha
Classifier: Intended Audience :: Developers
Classifier: Topic :: Software Development :: Build Tools
Classifier: License :: OSI Approved :: GNU General Public License v3 or later (GPLv3+)
Classifier: Programming Language :: Python :: 3.4
Classifier: Programming Language :: Python :: 3.5
Classifier: Programming Language :: Python :: 3.6
Classifier: Programming Language :: Python :: 3.7
Requires-Python: >=3.4
Requires-Dist: numpy
Requires-Dist: biopython
Requires-Dist: pandas
Requires-Dist: matplotlib
Requires-Dist: seaborn
Requires-Dist: ipfshttpclient
